setup.py
pbs_generator/Pbs.py
pbs_generator/__init__.py
pbs_generator/cli.py
pbs_generator.egg-info/PKG-INFO
pbs_generator.egg-info/SOURCES.txt
pbs_generator.egg-info/dependency_links.txt
pbs_generator.egg-info/entry_points.txt
pbs_generator.egg-info/requires.txt
pbs_generator.egg-info/top_level.txt
pbs_generator/CommandContainers/CommandContainerInterface.py
pbs_generator/CommandContainers/Modules.py
pbs_generator/CommandContainers/PbsCommands.py
pbs_generator/CommandContainers/ShellCommands.py
pbs_generator/CommandContainers/__init__.py