Metadata-Version: 1.1
Name: pbs-generator
Version: 1.5
Summary: A PBS script generator
Home-page: https://github.com/RowleyGroup/pbs-generator
Author: Mohamad Mohebifar
Author-email: mmohebifar@mun.ca
License: UNKNOWN
Download-URL: https://github.com/RowleyGroup/pbs-generator/tarball/1.0
Keywords: pbs-generator,rowley
Platform: UNKNOWN
